wik/__init__.py
wik/info.py
wik/wik.py
wik-2.0.1.dist-info/entry_points.txt
wik-2.0.1.dist-info/licenses/LICENSE
wik-2.0.1.dist-info/WHEEL
wik-2.0.1.dist-info/METADATA
wik-2.0.1.dist-info/RECORD
