Metadata-Version: 2.4
Name: wik
Version: 2.0.1
Summary: wik is used to get information about anything on the shell using Wikipedia
Author-email: Yash Singh <mailmeatyashsingh@gmail.com>
Requires-Python: >=3.0
Classifier: Programming Language :: Python :: 3
Classifier: License :: OSI Approved :: MIT License
Classifier: Operating System :: OS Independent
Classifier: Development Status :: 5 - Production/Stable
Classifier: Environment :: Console
License-File: LICENSE
Requires-Dist: beautifulsoup4
Requires-Dist: requests
Requires-Dist: flit ; extra == "dev"
Project-URL: Home, https://github.com/yashsinghcodes/wik
Provides-Extra: dev
